websharecli/__init__.py
websharecli/api.py
websharecli/cli.py
websharecli/commands.py
websharecli/config.py
websharecli/data.py
websharecli/terminal.py
websharecli/util.py
websharecli/static/config.yaml
websharecli-2.2.2.dist-info/LICENSE
websharecli-2.2.2.dist-info/METADATA
websharecli-2.2.2.dist-info/WHEEL
websharecli-2.2.2.dist-info/entry_points.txt
websharecli-2.2.2.dist-info/top_level.txt
websharecli-2.2.2.dist-info/RECORD
