Metadata-Version: 2.1
Name: websharecli
Version: 2.2.2
Summary: webshare.cz CLI downloader
Home-page: https://github.com/tkrizek/websharecli
Author: Tomas Krizek
Author-email: tomas.krizek@mailbox.org
License: GPLv3
Classifier: Development Status :: 5 - Production/Stable
Classifier: Programming Language :: Python :: 3 :: Only
Classifier: Programming Language :: Python :: 3.6
Classifier: Environment :: Console
Classifier: Topic :: Communications :: File Sharing
Classifier: Topic :: Utilities
Classifier: License :: OSI Approved :: GNU General Public License v3 (GPLv3)
License-File: LICENSE
Requires-Dist: blessings
Requires-Dist: PyYAML
Requires-Dist: requests
Requires-Dist: xmltodict
